{
  "project_info": {
    "project_number": "1017256555338",
    "project_id": "webuy-a9585",
    "storage_bucket": "webuy-a9585.appspot.com"
  },
  "client": [
    {
      "client_info": {
        "mobilesdk_app_id": "1:1017256555338:android:7a885e493b495f828307b3",
        "android_client_info": {
          "package_name": "com.example.webuy"
        }
      },
      "oauth_client": [
        {
          "client_id": "1017256555338-dsme16e7ljc03hmhu042fpsv55dq7s0o.apps.googleusercontent.com",
          "client_type": 3
        }
      ],
      "api_key": [
        {
          "current_key": "AIzaSyAgYNdiffmNQaIK4Do-bqOAiCrgE4XaH8Q"
        }
      ],
      "services": {
        "appinvite_service": {
          "other_platform_oauth_client": [
            {
              "client_id": "1017256555338-dsme16e7ljc03hmhu042fpsv55dq7s0o.apps.googleusercontent.com",
              "client_type": 3
            }
          ]
        }
      }
    }
  ],
  "configuration_version": "1"
}